[
  {
    "ParameterKey": "KeyName",
    "ParameterValue": "${KeyName}"
  },
  {
    "ParameterKey": "NodeImageId",
    "ParameterValue": "${NodeImageId}"
  },
  {
    "ParameterKey": "NodeInstanceType",
    "ParameterValue": "${NodeInstanceType}"
  },
  {
    "ParameterKey": "NodeAutoScalingGroupMinSize",
    "ParameterValue": "${NodeAutoScalingGroupMinSize}"
  },
  {
    "ParameterKey": "NodeAutoScalingGroupMaxSize",
    "ParameterValue": "${NodeAutoScalingGroupMaxSize}"
  },
  {
    "ParameterKey": "NodeVolumeSize",
    "ParameterValue": "${NodeVolumeSize}"
  },
  {
    "ParameterKey": "ClusterName",
    "ParameterValue": "${ClusterName}"
  },
  {
    "ParameterKey": "ClusterVersion",
    "ParameterValue": "${ClusterVersion}"
  },
  {
    "ParameterKey": "NodeGroupName",
    "ParameterValue": "${NodeGroupName}"
  },
  {
    "ParameterKey": "UseSpotFleetInstances",
    "ParameterValue": "${UseSpotFleetInstances}"
  },
  {
    "ParameterKey": "VpcId",
    "ParameterValue": "${VpcId}"
  },
  {
    "ParameterKey": "SubnetsEksNodesPrivate",
    "ParameterValue": "${SubnetsEksNodesPrivate}"
  },
  {
    "ParameterKey": "SubnetsEksMasterPublic",
    "ParameterValue": "${SubnetsEksMasterPublic}"
  }
]





